{
    "connects":[
       {"name":"amqpConnect",
        "Addr":"amqp://admin:admin@10.20.20.80//dbees"}
    ],
    "channels":[
       {"name":"WorkChannel",
        "connect":"amqpConnect",
        "qos_count":1,
        "qos_size":0},
       {"name":"errChannel",
        "connect":"amqpConnect",
        "qos_count":1,
        "qos_size":0},
       {"name":"dlxChannel",
        "connect":"amqpConnect",
        "qos_count":1,
        "qos_size":0}
    ],
    "exchanges":[
       {"name":"smsExchange",
        "channel":"WorkChannel",
        "type":"direct",
        "durable":false,
        "auto_deleted":false,
        "internal":false,
        "no_wait":false,
         "ebind":[
           {"destination":"smsExchange","key":"major_Exchanges","no_wait":false}
         ],
        "args":{
            "alternate-exchange":"errServerExchange"
            }
        },
       {"name":"errServerExchange",
        "channel":"errChannel",
        "type":"fanout",
        "durable":false,
        "auto_deleted":false,
        "internal":true,
        "no_wait":false,
         "ebind":[
           {"destination":"errServerExchange","key":"error_Exchanges","no_wait":false}
         ]
        },
       {"name":"dlxExchange",
        "channel":"dlxChannel",
        "type":"fanout",
        "durable":false,
        "auto_deleted":false,
        "internal":true,
        "no_wait":false,
         "ebind":[
           {"destination":"dlxExchange","key":"backup_Exchanges","no_wait":false}
         ]
        }
    ],
    "queue":[
       {"name":"yf_manage_message",
        "channel":"WorkChannel",
        "durable":true,
        "auto_delete":false,
        "exclusive":false,
        "no_wait":false,
        "qbind":[
            {"Key":"major_Exchanges", "exchange_name":"smsExchange", "no_wait":false}
        ],
        "args":{
            "x-message-ttl":10,
            "x-dead-letter-exchange":"dlxExchange",
            "x-dead-letter-routing-key":"dlxQueue"
        }},
       {"name":"errServerQueue",
        "channel":"errChannel",
        "durable":true,
        "auto_delete":false,
        "exclusive":false,
        "no_wait":false,
        "qbind":[
            {"Key":"errServerQueue", "exchange_name":"errServerExchange", "no_wait":false}
        ],
        "args":{
          "x-message-ttl":10,
          "x-dead-letter-exchange":"dlxExchange",
          "x-dead-letter-routing-key":"dlxQueue"
        }},
       {"name":"dlxQueue",
        "channel":"dlxChannel",
        "durable":true,
        "auto_delete":false,
        "exclusive":false,
        "no_wait":false,
        "qbind":[
            {"Key":"dlxQueue", "exchange_name":"dlxExchange", "no_wait":false}
        ],
        "args":{
          "x-message-ttl":10,
          "x-dead-letter-exchange":"dlxExchange",
          "x-dead-letter-routing-key":"dlxQueue"
        }}
    ],
    "pusher":[
       {"name":"Pusher",
        "channel":"WorkChannel",
        "exchange":"smsExchange",
        "Key":"major_Exchanges",
        "mandatory":false,
        "immediate":false,
        "content_type":"text/plain",
        "delivery_mode":0}
    ],
    "popup":[
       {"name":"Poper",
        "channel":"WorkChannel",
        "q_name":"yf_manage_message",
        "consumer":"主交换机Consumer",
        "AutoACK":false,
        "exclusive":false,
        "no_local":false,
        "no_wait":false
       },
       {"name":"errPoper",
        "channel":"errChannel",
        "q_name":"errServerQueue",
        "consumer":"错误交换机Consumer",
        "AutoACK":false,
        "exclusive":false,
        "no_local":false,
        "no_wait":false
       },
       {"name":"dlxPoper",
        "channel":"dlxChannel",
        "q_name":"dlxQueue",
        "consumer":"备份交换机Consumer",
        "AutoACK":false,
        "exclusive":false,
        "no_local":false,
        "no_wait":false
       },
       {"name":"DBDataId",
        "channel":"WorkChannel",
        "q_name":"yf_sms_send",
        "consumer":"DBDataIdConsumer",
        "AutoACK":false,
        "exclusive":false,
        "no_local":false,
        "no_wait":false
       }
    ]
}
